{"logos":{"FR":"http://cdn.ci5.yp.ca/t/1525/57/15255700ab_t.gif","EN":"http://cdn.ci5.yp.ca/t/1525/57/15255700ab_t.gif"},"id":"1137483","merchantUrl":"http://www.yellowpages.ca/bus/Ontario/Guelph/Norm-s-Esso-Service/1137483.html?ypid=","address":{"prov":"ON","street":"67 Surrey St E","pcode":"N1H3P7","city":"Guelph"},"name":"Norm's Esso Service","categories":[{"name":"Emission Testing","isSensitive":false},{"name":"Auto Repair Garages","isSensitive":false},{"name":"Auto Diagnostic","isSensitive":false},{"name":"Car Repair & Service","isSensitive":false},{"name":"Car Brakes Service","isSensitive":false},{"name":"Gas Stations","isSensitive":false},{"name":"Tire Retailers","isSensitive":false},{"name":"Vehicle Towing","isSensitive":false}],"products":{"photos":[{"thmbUrl":"http://cdn.media.yp.ca/295433/1356361365955_t.jpg","url":"http://cdn.media.yp.ca/295433/1356361365955.jpg"},{"thmbUrl":"http://cdn.media.yp.ca/295433/1356361371420_t.jpg","url":"http://cdn.media.yp.ca/295433/1356361371420.jpg"},{"thmbUrl":"http://cdn.media.yp.ca/295433/1356361377224_t.jpg","url":"http://cdn.media.yp.ca/295433/1356361377224.jpg"},{"thmbUrl":"http://cdn.media.yp.ca/295433/1356361383579_t.jpg","url":"http://cdn.media.yp.ca/295433/1356361383579.jpg"},{"thmbUrl":"http://cdn.media.yp.ca/295433/1356361388362_t.jpg","url":"http://cdn.media.yp.ca/295433/1356361388362.jpg"},{"thmbUrl":"http://cdn.media.yp.ca/295433/1356361394994_t.jpg","url":"http://cdn.media.yp.ca/295433/1356361394994.jpg"},{"thmbUrl":"http://cdn.media.yp.ca/295433/1356361401800_t.jpg","url":"http://cdn.media.yp.ca/295433/1356361401800.jpg"},{"thmbUrl":"http://cdn.media.yp.ca/295433/1356361408284_t.jpg","url":"http://cdn.media.yp.ca/295433/1356361408284.jpg"},{"thmbUrl":"http://cdn.media.yp.ca/295433/1356361413341_t.jpg","url":"http://cdn.media.yp.ca/295433/1356361413341.jpg"},{"thmbUrl":"http://cdn.media.yp.ca/295433/1356361418857_t.jpg","url":"http://cdn.media.yp.ca/295433/1356361418857.jpg"}],"dispAd":[{"thmbUrl":"http://ci.yp.ca/l/1375/28/13752879ac_l.gif","url":"http://ci.yp.ca/f/1375/28/13752879ac_f.jpg"},{"thmbUrl":"http://ci.yp.ca/l/1525/56/15255699ab_l.gif","url":"http://ci.yp.ca/f/1525/56/15255699ab_f.jpg"},{"thmbUrl":"http://ci.yp.ca/l/1525/56/15255689ab_l.gif","url":"http://ci.yp.ca/f/1525/56/15255689ab_f.jpg"},{"thmbUrl":"http://ci.yp.ca/l/1375/27/13752772ac_l.gif","url":"http://ci.yp.ca/f/1375/27/13752772ac_f.jpg"},{"thmbUrl":"http://ci.yp.ca/l/1375/27/13752775ab_l.gif","url":"http://ci.yp.ca/f/1375/27/13752775ab_f.jpg"}],"webUrl":["http://www.normsesso.ca"],"videos":[],"profiles":[{"keywords":{"MthdPmt":["American Express","Cash","MasterCard","Visa"],"ProdServ":["Air Conditioning","Alignment","Batteries","Brakes","Diagnostics","Engine/Transmission/Clutch Repairs","Exhausts","Full Service Station","Gas Pumping","Heating and Cooling Systems","Oil Changes","Safety Checks","Tires","Tune-ups"],"LangSpk":["English"],"OpenHrs":["Monday 7:00 am - 9:00 pm","Tuesday 7:00 am - 9:00 pm","Wednesday 7:00 am - 9:00 pm","Thursday 7:00 am - 9:00 pm","Friday 7:00 am - 9:00 pm","Saturday 8:00 am - 6:00 pm","Sunday 9:00 am - 6:00 pm"],"GetThr":["Guelph's Downtown Service Station"]},"lang":"EN"},{"keywords":{"MthdPmt":["American Express","Cash","MasterCard","Visa"],"ProdServ":["Air Conditioning","Alignment","Batteries","Brakes","Diagnostics","Engine/Transmission/Clutch Repairs","Exhausts","Full Service Station","Gas Pumping","Heating and Cooling Systems","Oil Changes","Safety Checks","Tires","Tune-ups"],"LangSpk":["English"],"OpenHrs":["Monday 7:00 am - 9:00 pm","Tuesday 7:00 am - 9:00 pm","Wednesday 7:00 am - 9:00 pm","Thursday 7:00 am - 9:00 pm","Friday 7:00 am - 9:00 pm","Saturday 8:00 am - 6:00 pm","Sunday 9:00 am - 6:00 pm"],"GetThr":["Guelph's Downtown Service Station"]},"lang":"FR"},{"keywords":{"MthdPmt":["American Express","Cash","MasterCard","Visa"],"ProdServ":["Air Conditioning","Alignment","Batteries","Brakes","Diagnostics","Engine/Transmission/Clutch Repairs","Exhausts","Full Service Station","Gas Pumping","Heating and Cooling Systems","Oil Changes","Safety Checks","Tires","Tune-ups"],"LangSpk":["English"],"OpenHrs":["Monday 7:00 am - 9:00 pm","Tuesday 7:00 am - 9:00 pm","Wednesday 7:00 am - 9:00 pm","Thursday 7:00 am - 9:00 pm","Friday 7:00 am - 9:00 pm","Saturday 8:00 am - 6:00 pm","Sunday 9:00 am - 6:00 pm"],"GetThr":["Guelph's Downtown Service Station"]},"lang":"EN"}]},"geoCode":{"longitude":"-80.2436953783","latitude":"43.5433495223"},"phones":[{"num":"6031","dispNum":"519-822-6031","type":"primary","nxx":"822","npa":"519"}]}