{"logos":{"FR":"http://cdn.ci2.yp.ca/t/1531/31/15313141aa_t.gif","EN":"http://cdn.ci2.yp.ca/t/1531/31/15313141aa_t.gif"},"id":"28750","merchantUrl":"http://www.yellowpages.ca/bus/Ontario/North-York/Academy-Auto-Collision-Ltd/28750.html?ypid=","address":{"prov":"ON","street":"2207 Jane St","pcode":"M3M1A5","city":"North York"},"name":"Academy Auto Collision Ltd","categories":[{"name":"Auto Body Repair & Painting Shops","isSensitive":false}],"products":{"photos":[],"dispAd":[],"webUrl":["http://www.academyautocollisionltd.com"],"videos":[{"universalUrl":"http://llrd.yellowpages.ca/o37/fc/63776031001/63776031001_1443308310001_74521-v1.mp4","thmbUrl":"http://yellowpage.vo.llnwd.net/o37/63776031001/63776031001_1443289257001_th-1443222126001.jpg?pubId=63776031001","url":"http://cdn.media.yp.ca/74521/1328567707219.flv"}],"profiles":[{"keywords":{"MthdPmt":["Interac","MasterCard","Visa"],"Special":["Customized Repairs","Insurance Claims","Private Repairs"],"ProdServ":["Auto Body Repair & Painting","Collision Repairs","Customized Work","Dent Repairs","Frame & Unibody Straightenning","Free Service Vehicles","Glass Repairs","Hail Damage Repairs","Insurance Claims","Mechanical Repairs","Towing Services","Wheel Alignment"],"LangSpk":["English","Italian","Spanish"],"OpenHrs":["Monday 8:00 am - 6:00 pm","Tuesday 8:00 am - 6:00 pm","Wednesday 8:00 am - 6:00 pm","Thursday 8:00 am - 6:00 pm","Friday 8:00 am - 6:00 pm","Saturday 8:00 am - 12:00 am"],"GetThr":["Jane / North of Wilson"]},"lang":"EN"},{"keywords":{"MthdPmt":["Interac","MasterCard","Visa"],"Special":["Customized Repairs","Insurance Claims","Private Repairs"],"ProdServ":["Auto Body Repair & Painting","Collision Repairs","Customized Work","Dent Repairs","Frame & Unibody Straightenning","Free Service Vehicles","Glass Repairs","Hail Damage Repairs","Insurance Claims","Mechanical Repairs","Towing Services","Wheel Alignment"],"LangSpk":["English","Italian","Spanish"],"OpenHrs":["Monday 8:00 am - 6:00 pm","Tuesday 8:00 am - 6:00 pm","Wednesday 8:00 am - 6:00 pm","Thursday 8:00 am - 6:00 pm","Friday 8:00 am - 6:00 pm","Saturday 8:00 am - 12:00 am"],"GetThr":["Jane / North of Wilson"]},"lang":"FR"}]},"geoCode":{"longitude":"-79.5091256375","latitude":"43.7229129718"},"phones":[{"num":"7821","dispNum":"416-247-7821","type":"primary","nxx":"247","npa":"416"}]}